{
  "app": "npx ts-node --prefer-ts-exts bin/cdk.ts",
  "watch": {
    "include": ["**"],
    "exclude": [
      "README.md",
      "cdk*.json",
      "**/*.d.ts",
      "**/*.js",
      "tsconfig.json",
      "package*.json",
      "yarn.lock",
      "node_modules",
      "test"
    ]
  },
  "context": {
    "app": {
      "name": "connect-hours-of-operation",
      "primaryRegion": "us-west-2",
      "tableName": "CCaS-Connect-Hours-Of-Operation-Table-Prod-Default",
      "partitionKeyName": "exp",
      "sortKeyName": "id",
      "readCapacity": 5,
      "minWriteCapacity": 1,
      "maxWriteCapacity": 10,
      "deletionProtection": true,
      "removalPolicy": "RETAIN",
      "pointInTimeRecovery": true,
      "ttlAttribute": "ttl",
      "multiRegionConsistency": "STRONG",
      "replicaRegions": ["us-east-1"],
      "witnessRegion": "us-east-2",
      "resourceTags": [
        { "key": "Project", "value": "connect-hours-of-operation" },
        { "key": "ManagedBy", "value": "CDK" },
        { "key": "Environment", "value": "Prod" }
      ]
    },

    "@aws-cdk/core:checkSecretUsage": true,
    "@aws-cdk/core:target-partitions": ["aws", "aws-cn"],
    "@aws-cdk/core:validateSnapshotRemovalPolicy": true,
    "@aws-cdk/core:enablePartitionLiterals": true,
    "@aws-cdk/core:includePrefixInUniqueNameGeneration": true,
    "@aws-cdk/core:explicitStackTags": true,
    "@aws-cdk/core:cfnIncludeRejectComplexResourceUpdateCreatePolicyIntrinsics": true,
    "@aws-cdk/core:enableAdditionalMetadataCollection": true,
    "@aws-cdk/core:aspectPrioritiesMutating": true,

    "@aws-cdk/custom-resources:logApiResponseDataPropertyTrueDefault": false,

    "@aws-cdk/aws-dynamodb:resourcePolicyPerReplica": true,
    "@aws-cdk/aws-dynamodb:retainTableReplica": true
  }
}
